Workbook

Sheet Read me
B2: AureonCare video library — production tracker
B5: What this is | C5: A tracker for the 32 single-feature training videos planned in docs/demo/VIDEO_LIBRARY_PLAN.md, plus 6 backlog ideas and the one prep task that precedes them. Each video runs 1-2 minutes and covers one module feature end to end.
B6: Status today | C6: Plan only. Nothing has been produced yet. The Google Meet recording in docs/google-verification/ exists for Google's OAuth review and can be re-edited into video V26.
B7: Sheets | C7: Video Tracker — the working list, one row per video. Dashboard — counts and completion, all formula-driven. Lists — dropdown values; edit here to change the options.
B9: How to use it | C9: Fill in the yellow columns only: Owner, Status, the four stage columns, the three dates, Video URL and Notes. Everything else is reference data from the plan, and Progress / Days to target are formulas — do not overwrite them.
B10: Progress | C10: Counts how many of Script / Recorded / Edited / Reviewed are set to Yes, out of four.
B11: Days to target | C11: Target publish minus today. Blank once Actual publish is filled in. Negative and unpublished turns red.
B13: Status meanings | C13: Not started · Scripting (writing the beat sheet) · Recording (driving the app) · Editing (captions, titles, mp4) · In review (SME check) · Approved (SME signed off, not yet posted) · Published (live to viewers) · On hold
B15: Example row | C15: V03 | Wave 1 | P0 | Book an appointment | Scheduling ▸ Calendar | Front desk | 2 | ... | Owner: Product marketing | Status: Editing | Script Yes | Recorded Yes | Edited In progress | Reviewed No | Progress 50% | Start 2026-08-10 | Target 2026-08-24 | URL blank until published
B17: Conventions | C17: 1280x720, no audio in v1 (captions carry the teaching), 5s title card + 10s why-this-matters + 60-90s journey + 10s recap. Synthetic data only, with the demo-environment watermark. Personas from docs/demo/DEMO_SCENARIOS.md.
B18: Re-cut trigger | C18: Any change to the app shell, a module's tab layout, or a journey's step order invalidates the affected video. Keep every video script-driven so a re-cut is cheap.

Sheet Dashboard
B2: Dashboard — recalculates from the Video Tracker
B4: Overall
B5: Items tracked | C5: =COUNTA('Video Tracker'!$A$3:$A$41) -> 39
B6: Videos planned | C6: =COUNTIF('Video Tracker'!$B$3:$B$41,"<>Prep") -> 38
B7: Published | C7: =COUNTIF('Video Tracker'!$K$3:$K$41,"Published") -> 0
B8: In flight (started, not published) | C8: =COUNTA('Video Tracker'!$A$3:$A$41)-COUNTIF('Video Tracker'!$K$3:$K$41,"Not started")-COUNTIF('Video Tracker'!$K$3:$K$41,"Published")-COUNTIF('Video Tracker'!$K$3:$K$41,"On hold") -> 10
B9: Not started | C9: =COUNTIF('Video Tracker'!$K$3:$K$41,"Not started") -> 29
B10: Overall completion | C10: =IFERROR(AVERAGE('Video Tracker'!$P$3:$P$41),0) -> 0.19230769
B11: Planned runtime (min) | C11: =SUM('Video Tracker'!$G$3:$G$41) -> 73.4
B12: Published runtime (min) | C12: =SUMIF('Video Tracker'!$K$3:$K$41,"Published",'Video Tracker'!$G$3:$G$41) -> 0
B14: By wave
B15: Wave | C15: Videos | D15: Published | E15: Complete | F15: Runtime (min)
B16: Prep | C16: =COUNTIF('Video Tracker'!$B$3:$B$41,$B16) -> 1 | D16: =COUNTIFS('Video Tracker'!$B$3:$B$41,$B16,'Video Tracker'!$K$3:$K$41,"Published") -> 0 | E16: =IFERROR(AVERAGEIF('Video Tracker'!$B$3:$B$41,$B16,'Video Tracker'!$P$3:$P$41),0) -> 0.75 | F16: =SUMIF('Video Tracker'!$B$3:$B$41,$B16,'Video Tracker'!$G$3:$G$41) -> 0
B17: Wave 1 | C17: =COUNTIF('Video Tracker'!$B$3:$B$41,$B17) -> 8 | D17: =COUNTIFS('Video Tracker'!$B$3:$B$41,$B17,'Video Tracker'!$K$3:$K$41,"Published") -> 0 | E17: =IFERROR(AVERAGEIF('Video Tracker'!$B$3:$B$41,$B17,'Video Tracker'!$P$3:$P$41),0) -> 0.75 | F17: =SUMIF('Video Tracker'!$B$3:$B$41,$B17,'Video Tracker'!$G$3:$G$41) -> 13.5
B18: Wave 2 | C18: =COUNTIF('Video Tracker'!$B$3:$B$41,$B18) -> 8 | D18: =COUNTIFS('Video Tracker'!$B$3:$B$41,$B18,'Video Tracker'!$K$3:$K$41,"Published") -> 0 | E18: =IFERROR(AVERAGEIF('Video Tracker'!$B$3:$B$41,$B18,'Video Tracker'!$P$3:$P$41),0) -> 0.09375 | F18: =SUMIF('Video Tracker'!$B$3:$B$41,$B18,'Video Tracker'!$G$3:$G$41) -> 20.4
B19: Wave 3 | C19: =COUNTIF('Video Tracker'!$B$3:$B$41,$B19) -> 7 | D19: =COUNTIFS('Video Tracker'!$B$3:$B$41,$B19,'Video Tracker'!$K$3:$K$41,"Published") -> 0 | E19: =IFERROR(AVERAGEIF('Video Tracker'!$B$3:$B$41,$B19,'Video Tracker'!$P$3:$P$41),0) -> 0 | F19: =SUMIF('Video Tracker'!$B$3:$B$41,$B19,'Video Tracker'!$G$3:$G$41) -> 13
B20: Wave 4 | C20: =COUNTIF('Video Tracker'!$B$3:$B$41,$B20) -> 9 | D20: =COUNTIFS('Video Tracker'!$B$3:$B$41,$B20,'Video Tracker'!$K$3:$K$41,"Published") -> 0 | E20: =IFERROR(AVERAGEIF('Video Tracker'!$B$3:$B$41,$B20,'Video Tracker'!$P$3:$P$41),0) -> 0 | F20: =SUMIF('Video Tracker'!$B$3:$B$41,$B20,'Video Tracker'!$G$3:$G$41) -> 17
B21: Backlog | C21: =COUNTIF('Video Tracker'!$B$3:$B$41,$B21) -> 6 | D21: =COUNTIFS('Video Tracker'!$B$3:$B$41,$B21,'Video Tracker'!$K$3:$K$41,"Published") -> 0 | E21: =IFERROR(AVERAGEIF('Video Tracker'!$B$3:$B$41,$B21,'Video Tracker'!$P$3:$P$41),0) -> 0 | F21: =SUMIF('Video Tracker'!$B$3:$B$41,$B21,'Video Tracker'!$G$3:$G$41) -> 9.5
B23: By status
B24: Status | C24: Count | D24: Share
B25: Not started | C25: =COUNTIF('Video Tracker'!$K$3:$K$41,$B25) -> 29 | D25: =IFERROR(C25/COUNTA('Video Tracker'!$A$3:$A$41),0) -> 0.74358974
B26: Scripting | C26: =COUNTIF('Video Tracker'!$K$3:$K$41,$B26) -> 0 | D26: =IFERROR(C26/COUNTA('Video Tracker'!$A$3:$A$41),0) -> 0
B27: Recording | C27: =COUNTIF('Video Tracker'!$K$3:$K$41,$B27) -> 0 | D27: =IFERROR(C27/COUNTA('Video Tracker'!$A$3:$A$41),0) -> 0
B28: Editing | C28: =COUNTIF('Video Tracker'!$K$3:$K$41,$B28) -> 0 | D28: =IFERROR(C28/COUNTA('Video Tracker'!$A$3:$A$41),0) -> 0
B29: In review | C29: =COUNTIF('Video Tracker'!$K$3:$K$41,$B29) -> 10 | D29: =IFERROR(C29/COUNTA('Video Tracker'!$A$3:$A$41),0) -> 0.25641026
B30: Approved | C30: =COUNTIF('Video Tracker'!$K$3:$K$41,$B30) -> 0 | D30: =IFERROR(C30/COUNTA('Video Tracker'!$A$3:$A$41),0) -> 0
B31: Published | C31: =COUNTIF('Video Tracker'!$K$3:$K$41,$B31) -> 0 | D31: =IFERROR(C31/COUNTA('Video Tracker'!$A$3:$A$41),0) -> 0
B32: On hold | C32: =COUNTIF('Video Tracker'!$K$3:$K$41,$B32) -> 0 | D32: =IFERROR(C32/COUNTA('Video Tracker'!$A$3:$A$41),0) -> 0
B34: By stage
B35: Stage | C35: Done | D35: In progress | E35: Not started
B36: Scripts | C36: =COUNTIF('Video Tracker'!$L$3:$L$41,"Yes") -> 10 | D36: =COUNTIF('Video Tracker'!$L$3:$L$41,"In progress") -> 0 | E36: =COUNTIF('Video Tracker'!$L$3:$L$41,"No") -> 29
B37: Recordings | C37: =COUNTIF('Video Tracker'!$M$3:$M$41,"Yes") -> 10 | D37: =COUNTIF('Video Tracker'!$M$3:$M$41,"In progress") -> 0 | E37: =COUNTIF('Video Tracker'!$M$3:$M$41,"No") -> 29
B38: Edits | C38: =COUNTIF('Video Tracker'!$N$3:$N$41,"Yes") -> 10 | D38: =COUNTIF('Video Tracker'!$N$3:$N$41,"In progress") -> 0 | E38: =COUNTIF('Video Tracker'!$N$3:$N$41,"No") -> 29
B39: Reviews | C39: =COUNTIF('Video Tracker'!$O$3:$O$41,"Yes") -> 0 | D39: =COUNTIF('Video Tracker'!$O$3:$O$41,"In progress") -> 0 | E39: =COUNTIF('Video Tracker'!$O$3:$O$41,"No") -> 39
B42: Every figure here is a formula over the Video Tracker sheet — update the tracker, not this sheet.

Sheet Lists
A1: Status | B1: Yes / No | C1: Wave | D1: Priority | E1: Owner | G1: Edit these lists to change the dropdown options on the Video Tracker.
A2: Not started | B2: No | C2: Prep | D2: P0 | E2: Unassigned
A3: Scripting | B3: In progress | C3: Wave 1 | D3: P1 | E3: Product marketing
A4: Recording | B4: Yes | C4: Wave 2 | D4: P2 | E4: Clinical SME
A5: Editing | C5: Wave 3 | D5: P3 | E5: Billing SME
A6: In review | C6: Wave 4 | D6: P4 | E6: Video editor
A7: Approved | C7: Backlog | E7: Engineering
A8: Published
A9: On hold

Sheet Video Tracker
A1: Video Tracker — one row per video · fill in the yellow columns only
A2: ID | B2: Wave | C2: Priority | D2: Title | E2: Module / path in app | F2: Audience | G2: Target (min) | H2: Journey (end to end) | I2: What it teaches | J2: Owner | K2: Status | L2: Script | M2: Recorded | N2: Edited | O2: Reviewed | P2: Progress | Q2: Start date | R2: Target publish | S2: Actual publish | T2: Days to target | U2: Video URL | V2: Notes
A3: P01 | B3: Prep | C3: P0 | D3: Shared recorder harness | E3: docs/google-verification/record-google-meet-demo.js | F3: Production | H3: Generalise the Google Meet recorder: shared fixtures, caption bar, title cards, cursor, mp4 output; one script per video. | I3: One-time cost that makes all 32 videos re-cuttable when the UI changes. | J3: Product marketing | K3: In review | L3: Yes | M3: Yes | N3: Yes | O3: No | P3: =COUNTIF(L3:O3,"Yes")/4 -> 0.75 | Q3: 46235 | T3: =IF(S3<>"","",IF(R3="","",R3-TODAY())) | V3: Harness at docs/demo/video-harness — branding kit and narration pipeline included.
A4: V01 | B4: Wave 1 | C4: P0 | D4: Find your way around AureonCare | E4: App shell · search · help | F4: Everyone | G4: 1.5 | H4: Sign in → three-pane shell → switch workspaces → universal search jumps to a patient → help drawer → AI assistant → theme and language switch. | I4: The navigation model, so every later video can say 'go to X ▸ Y'. | J4: Product marketing | K4: In review | L4: Yes | M4: Yes | N4: Yes | O4: No | P4: =COUNTIF(L4:O4,"Yes")/4 -> 0.75 | Q4: 46235 | T4: =IF(S4<>"","",IF(R4="","",R4-TODAY())) | V4: Recorded, branded (logo bumper, caption-bar mark, outro) and narrated. Voice is placeholder TTS — re-render with VOICE_ENGINE=files before publishing.
A5: V02 | B5: Wave 1 | C5: P0 | D5: Register a new patient | E5: Patients ▸ Patient Records | F5: Front desk | G5: 1.5 | H5: New Patient → demographics, contact, insurance, emergency contact → save → record opens → set status → invite to portal. | I5: Which fields matter downstream: insurance drives claims, email drives the portal. | J5: Product marketing | K5: In review | L5: Yes | M5: Yes | N5: Yes | O5: No | P5: =COUNTIF(L5:O5,"Yes")/4 -> 0.75 | Q5: 46235 | T5: =IF(S5<>"","",IF(R5="","",R5-TODAY())) | V5: Recorded, branded (logo bumper, caption-bar mark, outro) and narrated. Voice is placeholder TTS — re-render with VOICE_ENGINE=files before publishing.
A6: V03 | B6: Wave 1 | C6: P0 | D6: Book an appointment | E6: Scheduling ▸ Calendar | F6: Front desk | G6: 2 | H6: Day/week/month views → pick a slot → New Appointment (patient, provider, type, duration, telehealth) → save → reschedule → cancel with reason → reminders. | I6: Appointment type drives duration, and cancelling is not deleting. | J6: Product marketing | K6: In review | L6: Yes | M6: Yes | N6: Yes | O6: No | P6: =COUNTIF(L6:O6,"Yes")/4 -> 0.75 | Q6: 46235 | T6: =IF(S6<>"","",IF(R6="","",R6-TODAY())) | V6: Recorded, branded (logo bumper, caption-bar mark, outro) and narrated. Voice is placeholder TTS — re-render with VOICE_ENGINE=files before publishing.
A7: V04 | B7: Wave 1 | C7: P0 | D7: Read your day on the dashboard | E7: Home ▸ Dashboard | F7: Everyone | G7: 1 | H7: Metric tiles and what each counts → appointments quick view → tasks quick view → revenue quick view → click through to the module. | I7: The dashboard is a launchpad, not a report. | J7: Product marketing | K7: In review | L7: Yes | M7: Yes | N7: Yes | O7: No | P7: =COUNTIF(L7:O7,"Yes")/4 -> 0.75 | Q7: 46235 | T7: =IF(S7<>"","",IF(R7="","",R7-TODAY())) | V7: Recorded, branded (logo bumper, caption-bar mark, outro) and narrated. Voice is placeholder TTS — re-render with VOICE_ENGINE=files before publishing.
A8: V05 | B8: Wave 1 | C8: P0 | D8: Document a visit | E8: Patients ▸ Patient Records | F8: Clinician | G8: 2 | H8: Open the chart → history timeline → new clinical record → chief complaint and notes → vitals → allergies → save → appears on timeline and in portal. | I8: The chart is the single source of truth, and the patient sees what you save. | J8: Product marketing | K8: In review | L8: Yes | M8: Yes | N8: Yes | O8: No | P8: =COUNTIF(L8:O8,"Yes")/4 -> 0.75 | Q8: 46235 | T8: =IF(S8<>"","",IF(R8="","",R8-TODAY())) | V8: Recorded, branded (logo bumper, caption-bar mark, outro) and narrated. Voice is placeholder TTS — re-render with VOICE_ENGINE=files before publishing.
A9: V06 | B9: Wave 1 | C9: P0 | D9: Run a telehealth visit | E9: Clinical ▸ Telehealth | F9: Clinician | G9: 2 | H9: Active provider banner → New Session from an appointment → attach pre-session consent form → join link → Join → end → session under Recent. | I9: Scheduled session vs Instant meeting; pre-session forms land in the portal. | J9: Product marketing | K9: In review | L9: Yes | M9: Yes | N9: Yes | O9: No | P9: =COUNTIF(L9:O9,"Yes")/4 -> 0.75 | Q9: 46235 | T9: =IF(S9<>"","",IF(R9="","",R9-TODAY())) | V9: Recorded, branded (logo bumper, caption-bar mark, outro) and narrated. Voice is placeholder TTS — re-render with VOICE_ENGINE=files before publishing.
A10: V07 | B10: Wave 1 | C10: P0 | D10: Create and submit a claim | E10: Billing ▸ Claims | F10: Billing | G10: 2 | H10: New Claim from a completed encounter → payer, codes, charges → save draft → validate → submit to clearinghouse → status Submitted → where rejections surface. | I10: The claim states and what each one means for cash. | J10: Product marketing | K10: In review | L10: Yes | M10: Yes | N10: Yes | O10: No | P10: =COUNTIF(L10:O10,"Yes")/4 -> 0.75 | Q10: 46235 | T10: =IF(S10<>"","",IF(R10="","",R10-TODAY())) | V10: Recorded, branded (logo bumper, caption-bar mark, outro) and narrated. Voice is placeholder TTS — re-render with VOICE_ENGINE=files before publishing.
A11: V08 | B11: Wave 1 | C11: P0 | D11: What your patients see | E11: Patients ▸ Patient Portal | F11: Front desk · clinician | G11: 1.5 | H11: Portal as the patient: overview → appointments → diagnoses → prescriptions → records → forms requested → complete a form → submission appears staff-side. | I11: Staff can answer portal questions, and know what publishing exposes. | J11: Product marketing | K11: In review | L11: Yes | M11: Yes | N11: Yes | O11: No | P11: =COUNTIF(L11:O11,"Yes")/4 -> 0.75 | Q11: 46235 | T11: =IF(S11<>"","",IF(R11="","",R11-TODAY())) | V11: Recorded, branded (logo bumper, caption-bar mark, outro) and narrated. Voice is placeholder TTS — re-render with VOICE_ENGINE=files before publishing.
A12: V09 | B12: Wave 2 | C12: P1 | D12: Get a pre-authorization approved | E12: Billing ▸ Pre-Authorizations | F12: Billing | G12: 2.5 | H12: New pre-auth against payer and service → clinical justification → submit → track Submitted → Approved/Denied → link to appointment and claim. | I12: Do this before the visit, not after the denial. | J12: Unassigned | K12: Not started | L12: No | M12: No | N12: No | O12: No | P12: =COUNTIF(L12:O12,"Yes")/4 -> 0 | T12: =IF(S12<>"","",IF(R12="","",R12-TODAY())) | V12: Re-rendered against the merged UI.
A13: V10 | B13: Wave 2 | C13: P1 | D13: Work a denial to resolution | E13: Billing ▸ Denials | F13: Billing | G13: 2.7 | H13: Denials queue → open a denied claim → read the denial reason → correct the coding → resubmit → track the appeal. | I13: The denial reason codes staff actually see, and the resubmit path. | J13: Unassigned | K13: Not started | L13: No | M13: No | N13: No | O13: No | P13: =COUNTIF(L13:O13,"Yes")/4 -> 0 | T13: =IF(S13<>"","",IF(R13="","",R13-TODAY())) | V13: Re-rendered against the merged UI.
A14: V11 | B14: Wave 2 | C14: P1 | D14: Record a payment and post it | E14: Billing ▸ Payments / Payment Postings | F14: Billing | G14: 2.9 | H14: Record an insurance payment → allocate across claim lines → patient responsibility → balance updates on the claim and in Receivables. | I14: Why unposted payments distort AR. | J14: Unassigned | K14: Not started | L14: No | M14: No | N14: No | O14: No | P14: =COUNTIF(L14:O14,"Yes")/4 -> 0 | T14: =IF(S14<>"","",IF(R14="","",R14-TODAY())) | V14: Re-rendered against the merged UI.
A15: V12 | B15: Wave 2 | C15: P1 | D15: Quote, invoice, get paid | E15: Billing ▸ Quotes & Invoices | F15: Front desk · billing | G15: 2.3 | H15: Build a quote from the catalogue → convert to invoice → send → take a card payment via Stripe → receipt → invoice closes and Accounting reflects it. | I15: The self-pay path, which the claims videos do not cover. | J15: Unassigned | K15: Not started | L15: No | M15: No | N15: No | O15: No | P15: =COUNTIF(L15:O15,"Yes")/4 -> 0 | T15: =IF(S15<>"","",IF(R15="","",R15-TODAY())) | V15: Re-rendered against the merged UI.
A16: V13 | B16: Wave 2 | C16: P1 | D16: Prescribe and send electronically | E16: Clinical ▸ Diagnoses ▸ e-Prescribe | F16: Clinician | G16: 2.4 | H16: New prescription → drug, dose, refills → interaction and allergy check fires → choose the patient's pharmacy → send via Surescripts → status → appears in portal. | I16: The safety checks are the point; do not click past them. | J16: Unassigned | K16: Not started | L16: No | M16: No | N16: No | O16: No | P16: =COUNTIF(L16:O16,"Yes")/4 -> 0 | T16: =IF(S16<>"","",IF(R16="","",R16-TODAY())) | V16: Re-rendered against the merged UI.
A17: V14 | B17: Wave 2 | C17: P1 | D17: Order a lab and file the result | E17: Clinical ▸ Laboratories | F17: Clinician | G17: 2.6 | H17: New lab order → panel and diagnosis → transmit to Labcorp → track status → result returns → review, flag abnormal, file to chart → notify patient. | I17: The ordering loop closes in the chart, not in email. | J17: Unassigned | K17: Not started | L17: No | M17: No | N17: No | O17: No | P17: =COUNTIF(L17:O17,"Yes")/4 -> 0 | T17: =IF(S17<>"","",IF(R17="","",R17-TODAY())) | V17: Re-rendered against the merged UI.
A18: V15 | B18: Wave 2 | C18: P1 | D18: Record a diagnosis | E18: Clinical ▸ Diagnoses | F18: Clinician | G18: 2.3 | H18: New diagnosis → ICD-10 search → status (active/resolved/chronic) → onset → link to encounter → flows onto claims and the portal. | I18: Diagnosis quality drives claim acceptance. | J18: Product marketing | K18: In review | L18: Yes | M18: Yes | N18: Yes | O18: No | P18: =COUNTIF(L18:O18,"Yes")/4 -> 0.75 | Q18: 46246 | T18: =IF(S18<>"","",IF(R18="","",R18-TODAY())) | V18: Re-recorded against the relocated nav (Clinical, not Patients) and the new patient picker on the standalone form. Narrated with google/en-US-Neural2-D to match the rest of the library. Re-rendered against the merged UI.
A19: V16 | B19: Wave 2 | C19: P1 | D19: Set up appointment types and provider schedules | E19: Scheduling ▸ Setup / Providers | F19: Admin | G19: 2.7 | H19: Appointment types with durations, colours, telehealth defaults → provider working hours → time off → calendar reflects both immediately. | I19: Most scheduling complaints are a configuration problem, fixed here. | J19: Unassigned | K19: Not started | L19: No | M19: No | N19: No | O19: No | P19: =COUNTIF(L19:O19,"Yes")/4 -> 0 | T19: =IF(S19<>"","",IF(R19="","",R19-TODAY())) | V19: Re-rendered against the merged UI.
A20: V17 | B20: Wave 3 | C20: P2 | D20: Let patients book themselves | E20: Public booking page | F20: Admin · front desk | G20: 2 | H20: Configure bookable types → share the public link → patient flow (Select Type → Choose Time → Your Info → Confirm) → booking lands on the calendar. | I20: What patients can and cannot self-book. | J20: Unassigned | K20: Not started | L20: No | M20: No | N20: No | O20: No | P20: =COUNTIF(L20:O20,"Yes")/4 -> 0 | T20: =IF(S20<>"","",IF(R20="","",R20-TODAY()))
A21: V18 | B21: Wave 3 | C21: P2 | D21: Fill a cancelled slot from the waitlist | E21: Scheduling ▸ Waitlist | F21: Front desk | G21: 1.5 | H21: Add a patient with priority and flexibility → a cancellation opens a slot → notify next patient → confirm → appointment created, entry clears. | I21: The waitlist only works if entries carry real availability windows. | J21: Unassigned | K21: Not started | L21: No | M21: No | N21: No | O21: No | P21: =COUNTIF(L21:O21,"Yes")/4 -> 0 | T21: =IF(S21<>"","",IF(R21="","",R21-TODAY()))
A22: V19 | B22: Wave 3 | C22: P2 | D22: Collect intake and consent before arrival | E22: Patients ▸ Patient Intake | F22: Front desk | G22: 2 | H22: Build an intake flow from forms → send to patient → patient completes in portal → staff review → data lands on chart → consent stored with timestamp. | I22: Intake forms vs intake flows vs consent forms. | J22: Unassigned | K22: Not started | L22: No | M22: No | N22: No | O22: No | P22: =COUNTIF(L22:O22,"Yes")/4 -> 0 | T22: =IF(S22<>"","",IF(R22="","",R22-TODAY()))
A23: V20 | B23: Wave 3 | C23: P2 | D23: Build a form template and read the submissions | E23: Patients ▸ Form Templates | F23: Admin | G23: 2 | H23: New template → field types and required fields → publish → assign to a patient → submissions tab → open a completed submission → form audit log. | I23: Forms are versioned and audited; edit deliberately. | J23: Unassigned | K23: Not started | L23: No | M23: No | N23: No | O23: No | P23: =COUNTIF(L23:O23,"Yes")/4 -> 0 | T23: =IF(S23<>"","",IF(R23="","",R23-TODAY()))
A24: V21 | B24: Wave 3 | C24: P2 | D24: Answer a question with a report | E24: Insights ▸ Reports | F24: Manager | G24: 1.5 | H24: Operational vs financial vs insurance categories → open No-Show Report → date range → chart type → read the trend → export to PDF/Excel. | I24: Which report answers which question. | J24: Unassigned | K24: Not started | L24: No | M24: No | N24: No | O24: No | P24: =COUNTIF(L24:O24,"Yes")/4 -> 0 | T24: =IF(S24<>"","",IF(R24="","",R24-TODAY()))
A25: V22 | B25: Wave 3 | C25: P2 | D25: Build a custom report and export it | E25: Insights ▸ Custom Report | F25: Manager | G25: 2 | H25: Custom Report → data source, columns, filters, grouping → preview → save → export. | I25: The escape hatch when no standard report fits. | J25: Unassigned | K25: Not started | L25: No | M25: No | N25: No | O25: No | P25: =COUNTIF(L25:O25,"Yes")/4 -> 0 | T25: =IF(S25<>"","",IF(R25="","",R25-TODAY()))
A26: V23 | B26: Wave 3 | C26: P2 | D26: Package services and run a promotion | E26: Growth ▸ Service Catalog | F26: Manager | G26: 2 | H26: Create a service with price and duration → bundle into a package → category → promotion with validity window → appears in booking and quotes → statistics. | I26: Pricing lives in one place and flows everywhere. | J26: Unassigned | K26: Not started | L26: No | M26: No | N26: No | O26: No | P26: =COUNTIF(L26:O26,"Yes")/4 -> 0 | T26: =IF(S26<>"","",IF(R26="","",R26-TODAY()))
A27: V24 | B27: Wave 4 | C27: P3 | D27: Configure your clinic | E27: Settings ▸ Practice | F27: Admin | G27: 2 | H27: Clinic identity, address, timezone, currency → working hours → appointment rules (slot length, buffers, booking window). | I27: These settings are upstream of scheduling behaviour. | J27: Unassigned | K27: Not started | L27: No | M27: No | N27: No | O27: No | P27: =COUNTIF(L27:O27,"Yes")/4 -> 0 | T27: =IF(S27<>"","",IF(R27="","",R27-TODAY()))
A28: V25 | B28: Wave 4 | C28: P3 | D28: Add users and control what they can see | E28: Settings ▸ Access Control | F28: Admin | G28: 2 | H28: Invite a user → assign role → permissions matrix → module-level effect → multi-role users → plan gating vs role gating. | I28: The two independent gates that explain 'why can't I see this module'. | J28: Unassigned | K28: Not started | L28: No | M28: No | N28: No | O28: No | P28: =COUNTIF(L28:O28,"Yes")/4 -> 0 | T28: =IF(S28<>"","",IF(R28="","",R28-TODAY()))
A29: V26 | B29: Wave 4 | C29: P3 | D29: Connect a video provider | E29: Settings ▸ Telehealth Setup | F29: Admin | G29: 1.5 | H29: Telehealth Setup → connect an account via OAuth → test connection → enable → becomes the active provider in Telehealth. | I29: Re-edit of the existing Google Meet recording — cheapest video in the list. | J29: Unassigned | K29: Not started | L29: No | M29: No | N29: No | O29: No | P29: =COUNTIF(L29:O29,"Yes")/4 -> 0 | T29: =IF(S29<>"","",IF(R29="","",R29-TODAY()))
A30: V27 | B30: Wave 4 | C30: P3 | D30: Connect pharmacy, lab and payment partners | E30: Settings ▸ Integrations | F30: Admin | G30: 2 | H30: Integrations → Surescripts, Labcorp, Optum, Stripe → credentials → sandbox vs live → enable → where each shows up in daily work. | I30: An integration must be configured before it can be enabled. | J30: Unassigned | K30: Not started | L30: No | M30: No | N30: No | O30: No | P30: =COUNTIF(L30:O30,"Yes")/4 -> 0 | T30: =IF(S30<>"","",IF(R30="","",R30-TODAY()))
A31: V28 | B31: Wave 4 | C31: P3 | D31: Stock: item to purchase order to receipt | E31: Operations ▸ Inventory | F31: Ops | G31: 2 | H31: Create an item with category and reorder point → stock levels → low-stock alert → purchase order to supplier → receive stock → levels update. | I31: The reorder point is what makes the alerts useful. | J31: Unassigned | K31: Not started | L31: No | M31: No | N31: No | O31: No | P31: =COUNTIF(L31:O31,"Yes")/4 -> 0 | T31: =IF(S31<>"","",IF(R31="","",R31-TODAY()))
... A35: V32 | B35: Wave 4 | C35: P3 | D35: Exchange data over FHIR | E35: Clinical ▸ FHIR Resources / Tracking | F35: IT | G35: 2 | H35: Browse resource types → inspect a Patient/Observation resource → FHIR Tracking shows exchanges and failures → retry a failed exchange. | I35: Where to look when a partner says 'we didn't get it'. | J35: Unassigned | K35: Not started | L35: No | M35: No | N35: No | O35: No | P35: =COUNTIF(L35:O35,"Yes")/4 -> 0 | T35: =IF(S35<>"","",IF(R35="","",R35-TODAY()))
A36: B01 | B36: Backlog | C36: P4 | D36: Notifications and tasks | E36: Cross-module | F36: Everyone | G36: 1.5 | H36: Assign a task → recipient is notified → complete it → the loop closes on the dashboard. | J36: Unassigned | K36: Not started | L36: No | M36: No | N36: No | O36: No | P36: =COUNTIF(L36:O36,"Yes")/4 -> 0 | T36: =IF(S36<>"","",IF(R36="","",R36-TODAY()))
A37: B02 | B37: Backlog | C37: P4 | D37: Merge duplicate patients | E37: Patients ▸ Patient Records | F37: Front desk | G37: 1.5 | H37: Identify duplicates → compare records → merge → verify history survived the merge. | J37: Unassigned | K37: Not started | L37: No | M37: No | N37: No | O37: No | P37: =COUNTIF(L37:O37,"Yes")/4 -> 0 | T37: =IF(S37<>"","",IF(R37="","",R37-TODAY()))
A38: B03 | B38: Backlog | C38: P4 | D38: Patient history and health metric trends | E38: Patients ▸ Patient History | F38: Clinician | G38: 1.5 | H38: Open history → health metrics over time → chart a vital → spot a trend across visits. | J38: Unassigned | K38: Not started | L38: No | M38: No | N38: No | O38: No | P38: =COUNTIF(L38:O38,"Yes")/4 -> 0 | T38: =IF(S38<>"","",IF(R38="","",R38-TODAY()))
A39: B04 | B39: Backlog | C39: P4 | D39: CRM and campaigns | E39: Growth ▸ CRM | F39: Manager | G39: 2 | H39: Lead capture → CRM pipeline → build a campaign → send → measure response. | J39: Unassigned | K39: Not started | L39: No | M39: No | N39: No | O39: No | P39: =COUNTIF(L39:O39,"Yes")/4 -> 0 | T39: =IF(S39<>"","",IF(R39="","",R39-TODAY()))
A40: B05 | B40: Backlog | C40: P4 | D40: Working in another language | E40: App shell | F40: Everyone | G40: 1.5 | H40: Switch language (en/es/fr/de/ar) → translated UI → right-to-left layout in Arabic. | J40: Unassigned | K40: Not started | L40: No | M40: No | N40: No | O40: No | P40: =COUNTIF(L40:O40,"Yes")/4 -> 0 | T40: =IF(S40<>"","",IF(R40="","",R40-TODAY()))
A41: B06 | B41: Backlog | C41: P4 | D41: Recurring appointments | E41: Scheduling ▸ Calendar | F41: Front desk | G41: 1.5 | H41: Create a recurring series → edit one occurrence vs the series → cancel the series. | J41: Unassigned | K41: Not started | L41: No | M41: No | N41: No | O41: No | P41: =COUNTIF(L41:O41,"Yes")/4 -> 0 | T41: =IF(S41<>"","",IF(R41="","",R41-TODAY()))
